cliqestimre/__init__.py
cliqestimre/clinetwork.cpython-311-darwin.so
cliqestimre-0.1.1.dist-info/LICENSE.txt
cliqestimre-0.1.1.dist-info/METADATA
cliqestimre-0.1.1.dist-info/WHEEL
cliqestimre-0.1.1.dist-info/top_level.txt
cliqestimre-0.1.1.dist-info/RECORD
